README.txt
setup.py
docs/HISTORY.txt
docs/INSTALL.txt
docs/LICENSE.GPL
docs/LICENSE.txt
medialog/__init__.py
medialog.abc.egg-info/PKG-INFO
medialog.abc.egg-info/SOURCES.txt
medialog.abc.egg-info/dependency_links.txt
medialog.abc.egg-info/entry_points.txt
medialog.abc.egg-info/namespace_packages.txt
medialog.abc.egg-info/not-zip-safe
medialog.abc.egg-info/requires.txt
medialog.abc.egg-info/top_level.txt
medialog/abc/__init__.py
medialog/abc/configure.zcml
medialog/abc/interfaces.py
medialog/abc/profiles.zcml
medialog/abc/schemaextender.py
medialog/abc/profiles/default/browserlayer.xml
medialog/abc/profiles/default/catalog.xml
medialog/abc/profiles/default/metadata.xml