Metadata-Version: 1.0
Name: medialog.abc
Version: 0.3.4
Summary: Adds fields to images.
Home-page: http://medialog.no
Author: Grieg Medialog [Espen Moe-Nilssen]
Author-email: espen@medialog.no
License: GPL
Keywords: plone zope subskins sector custom css
Platform: UNKNOWN
Classifier: Framework :: Plone
Classifier: Programming Language :: Python
Classifier: Topic :: Software Development :: Libraries :: Python Modules
